blast_extract/__init__.py
blast_extract/__main__.py
blast_extract/blasting.py
blast_extract/blastresult.py
blast_extract/extract_sequences.py
blast_extract/hash_sequences.py
blast_extract/seqtools.py
blast_extract-0.1.0.dist-info/LICENSE
blast_extract-0.1.0.dist-info/METADATA
blast_extract-0.1.0.dist-info/WHEEL
blast_extract-0.1.0.dist-info/entry_points.txt
blast_extract-0.1.0.dist-info/top_level.txt
blast_extract-0.1.0.dist-info/RECORD
