Metadata-Version: 2.1
Name: blast-extract
Version: 0.1.0
Summary: Provides tools to extract nucleotide sequences from a genome using NCBI BLAST
Home-page: https://github.com/jandeneweth/blast-extract
Author: Jan Deneweth
Author-email: jandeneweth@hotmail.com
License: UNKNOWN
Project-URL: Bug Tracker, https://github.com/jandeneweth/blast-extract/issues
Platform: UNKNOWN
Classifier: Programming Language :: Python :: 3
Classifier: Programming Language :: Python :: 3.10
Classifier: License :: OSI Approved :: GNU Affero General Public License v3 or later (AGPLv3+)
Classifier: Operating System :: OS Independent
Requires-Python: >=3.10
License-File: LICENSE
